client/__init__.py
client/client_app.py
client/client/__init__.py
client/client/add_contact.py
client/client/client_base.py
client/client/del_contact.py
client/client/main_window.py
client/client/main_window_conv.py
client/client/net_client.py
client/client/start_dialog.py
client/common/__init__.py
client/common/decor_1.py
client/common/decor_2.py
client/common/descript.py
client/common/errors.py
client/common/meta_detect.py
client/common/utils.py
client/common/variables.py
client/decorator/__init__.py
client/decorator/decor.py
client/logs/__init__.py
client/logs/config_client_log.py
client/logs/config_log_2.py
client/logs/config_server_log.py
MAA_PyQT5_messenger_client_app-0.0.1.dist-info/METADATA
MAA_PyQT5_messenger_client_app-0.0.1.dist-info/WHEEL
MAA_PyQT5_messenger_client_app-0.0.1.dist-info/top_level.txt
MAA_PyQT5_messenger_client_app-0.0.1.dist-info/RECORD
